dlt_source_notion/__init__.py
dlt_source_notion/client.py
dlt_source_notion/tests/__init__.py
dlt_source_notion/tests/test_noop.py
dlt_source_notion-0.0.9.dist-info/licenses/LICENSE
dlt_source_notion-0.0.9.dist-info/METADATA
dlt_source_notion-0.0.9.dist-info/WHEEL
dlt_source_notion-0.0.9.dist-info/top_level.txt
dlt_source_notion-0.0.9.dist-info/RECORD
