Metadata-Version: 2.4
Name: dlt-source-notion
Version: 0.0.9
Summary: A DLT source for notion
Author-email: Planet A GmbH <dev@planet-a.com>
Classifier: Programming Language :: Python :: 3.12
Classifier: License :: OSI Approved :: MIT License
Classifier: Operating System :: OS Independent
Requires-Python: >=3.12
License-File: LICENSE
Requires-Dist: dlt>=1.8.1
Requires-Dist: pydantic-api-sdk-notion>=0.0.37
Requires-Dist: pydantic>=2.10.6
Provides-Extra: show
Requires-Dist: dlt[duckdb]>=1.8.1; extra == "show"
Requires-Dist: streamlit>=1.41.1; extra == "show"
Requires-Dist: watchdog>=6.0.0; extra == "show"
Dynamic: license-file
